MLV_toolbox/InitializeNeighborhoods.py
MLV_toolbox/VecLD.py
MLV_toolbox/__init__.py
MLV_toolbox/applyCircularAperture.py
MLV_toolbox/averageProperty.py
MLV_toolbox/computeColorIndex.py
MLV_toolbox/computeGradientVectorField.py
MLV_toolbox/computeLength.py
MLV_toolbox/computeOrientation.py
MLV_toolbox/drawLinedrawing.py
MLV_toolbox/generateFeatureDensityMap.py
MLV_toolbox/getDistanceFromLineSegment.py
MLV_toolbox/getMATpropertyStats.py
MLV_toolbox/importSVG.py
MLV_toolbox/lineIntersection.py
MLV_toolbox/loadData.py
MLV_toolbox/randomlyShiftContours.py
MLV_toolbox/removeZeroLengthContours.py
MLV_toolbox/renderJunctions.py
MLV_toolbox/renderLinedrawing.py
MLV_toolbox/rotateLinedrawing.py
MLV_toolbox/wakatime_hack.py
MLV_toolbox/wakatime_hack.pywakatime_hack.py
MLV_toolbox_python-0.0.4.dist-info/METADATA
MLV_toolbox_python-0.0.4.dist-info/WHEEL
MLV_toolbox_python-0.0.4.dist-info/top_level.txt
MLV_toolbox_python-0.0.4.dist-info/RECORD
