Metadata-Version: 2.1
Name: MLV-toolbox-python
Version: 0.0.4
Summary: A tool for researchers to extract structural properties of contours such as orientation, length, curvature and junctions present in images
Home-page: https://github.com/sadmanca/MLV_toolbox_python
Author: Dirk Bernhardt-Walther, Sadman Hossain
Author-email: m.sadman.h@gmail.com
License: UNKNOWN
Project-URL: Roadmap, https://github.com/users/sadmanca/projects/4
Project-URL: Issues, https://github.com/sadmanca/MLV_toolbox_python/issues
Platform: UNKNOWN
Classifier: Development Status :: 2 - Pre-Alpha
Classifier: Intended Audience :: Science/Research
Classifier: Topic :: Scientific/Engineering :: Image Processing
Classifier: Natural Language :: English
Classifier: Programming Language :: Python :: 3
Classifier: Operating System :: OS Independent
Requires-Dist: numpy
Requires-Dist: scipy
Requires-Dist: matplotlib
Requires-Dist: opencv-python
Requires-Dist: tabulate
